Kalender/__init__.py
Kalender/fungsi_1.py
Kalender/fungsi_2.py
Kalender/fungsi_3.py
Kalender/fungsi_4.py
Kalender/fungsi_5.py
Kalender/fungsi_6.py
KALENDER-0.0.1.dist-info/METADATA
KALENDER-0.0.1.dist-info/WHEEL
KALENDER-0.0.1.dist-info/top_level.txt
KALENDER-0.0.1.dist-info/RECORD
